<annotation>
	<folder>futi16</folder>
	<filename>futi16_302.jpg</filename>
	<path>C:\Users\user\Desktop\研衔接\futi16\futi16_302.jpg</path>
	<source>
		<database>Unknown</database>
	</source>
	<size>
		<width>640</width>
		<height>480</height>
		<depth>3</depth>
	</size>
	<segmented>0</segmented>
	<object>
		<name>person</name>
		<pose>Unspecified</pose>
		<truncated>0</truncated>
		<difficult>0</difficult>
		<bndbox>
			<xmin>9</xmin>
			<ymin>148</ymin>
			<xmax>35</xmax>
			<ymax>271</ymax>
		</bndbox>
	</object>
	<object>
		<name>person</name>
		<pose>Unspecified</pose>
		<truncated>0</truncated>
		<difficult>0</difficult>
		<bndbox>
			<xmin>67</xmin>
			<ymin>118</ymin>
			<xmax>93</xmax>
			<ymax>225</ymax>
		</bndbox>
	</object>
	<object>
		<name>person</name>
		<pose>Unspecified</pose>
		<truncated>0</truncated>
		<difficult>0</difficult>
		<bndbox>
			<xmin>31</xmin>
			<ymin>117</ymin>
			<xmax>51</xmax>
			<ymax>194</ymax>
		</bndbox>
	</object>
	<object>
		<name>person</name>
		<pose>Unspecified</pose>
		<truncated>0</truncated>
		<difficult>0</difficult>
		<bndbox>
			<xmin>123</xmin>
			<ymin>98</ymin>
			<xmax>141</xmax>
			<ymax>162</ymax>
		</bndbox>
	</object>
</annotation>